dvtk/__init__.py
dvtk/cli.py
dvtk/default_metrics.py
dvtk/processor.py
dvtk/storage.py
dvtk/utils.py
dvtk-0.2.1.dist-info/METADATA
dvtk-0.2.1.dist-info/WHEEL
dvtk-0.2.1.dist-info/entry_points.txt
dvtk-0.2.1.dist-info/top_level.txt
dvtk-0.2.1.dist-info/RECORD
