Metadata-Version: 2.4
Name: dvtk
Version: 0.2.1
Summary: Lightweight package to validate/measure audio files in local or S3 directories.
Requires-Python: >=3.10
Requires-Dist: boto3>=1.38.29
Requires-Dist: librosa>=0.11.0
Requires-Dist: numpy>=2.0.2
Requires-Dist: onnxruntime-gpu>=1.20.2
Requires-Dist: requests>=2.32.3
Requires-Dist: torch>=2.7.0
Requires-Dist: torchaudio>=2.7.0
Requires-Dist: torchmetrics>=1.7.2
